officialeye-1.2.2.dist-info/METADATA
officialeye-1.2.2.dist-info/WHEEL
officialeye-1.2.2.dist-info/entry_points.txt
officialeye-1.2.2.dist-info/licenses/LICENSE
officialeye/__init__.py
officialeye/__version__.py
officialeye/_api/__init__.py
officialeye/_api/config.py
officialeye/_api/context.py
officialeye/_api/detection.py
officialeye/_api/future.py
officialeye/_api/image.py
officialeye/_api/mutator.py
officialeye/_api/template/__init__.py
officialeye/_api/template/feature.py
officialeye/_api/template/interpretation.py
officialeye/_api/template/interpretation_result.py
officialeye/_api/template/keypoint.py
officialeye/_api/template/match.py
officialeye/_api/template/matcher.py
officialeye/_api/template/matching_result.py
officialeye/_api/template/region.py
officialeye/_api/template/supervision_result.py
officialeye/_api/template/supervisor.py
officialeye/_api/template/template.py
officialeye/_api/template/template_interface.py
officialeye/_api_builtins/__init__.py
officialeye/_api_builtins/init.py
officialeye/_api_builtins/interpretation/__init__.py
officialeye/_api_builtins/interpretation/file.py
officialeye/_api_builtins/interpretation/file_temp.py
officialeye/_api_builtins/interpretation/ocr_tesseract.py
officialeye/_api_builtins/matcher/__init__.py
officialeye/_api_builtins/matcher/sift_flann.py
officialeye/_api_builtins/mutator/__init__.py
officialeye/_api_builtins/mutator/clahe.py
officialeye/_api_builtins/mutator/crop.py
officialeye/_api_builtins/mutator/grayscale.py
officialeye/_api_builtins/mutator/non_local_means_denoising.py
officialeye/_api_builtins/mutator/rotate.py
officialeye/_api_builtins/supervisor/__init__.py
officialeye/_api_builtins/supervisor/combinatorial.py
officialeye/_api_builtins/supervisor/least_squares_regression.py
officialeye/_cli/__init__.py
officialeye/_cli/context.py
officialeye/_cli/create.py
officialeye/_cli/main.py
officialeye/_cli/run.py
officialeye/_cli/show.py
officialeye/_cli/test.py
officialeye/_cli/ui.py
officialeye/_cli/utils.py
officialeye/_internal/__init__.py
officialeye/_internal/_types.py
officialeye/_internal/api/__init__.py
officialeye/_internal/api/detect.py
officialeye-1.2.2.dist-info/RECORD
