Metadata-Version: 2.1
Name: officialeye
Version: 1.2.2
Summary: AI-powered generic document-analysis tool
Author-Email: Alexander Mayorov <zb@zerobone.net>
License:                     GNU GENERAL PUBLIC LICENSE
Classifier: Development Status :: 5 - Production/Stable
Classifier: Operating System :: OS Independent
Classifier: Topic :: Scientific/Engineering :: Image Recognition
Classifier: Topic :: Scientific/Engineering :: Image Processing
Classifier: Topic :: Scientific/Engineering :: Artificial Intelligence
Classifier: License :: OSI Approved :: GNU General Public License v3 (GPLv3)
Project-URL: Homepage, https://github.com/ZeroBone/OfficialEye
Project-URL: Documentation, https://officialeye.zerobone.net
Project-URL: Issues, https://github.com/ZeroBone/OfficialEye/issues
Requires-Python: >=3.10
Requires-Dist: click>=8.1.7
Requires-Dist: numpy>=1.26.2
Requires-Dist: opencv-contrib-python-headless
Requires-Dist: pytesseract
Requires-Dist: pyyaml
Requires-Dist: strictyaml==1.7.3
Requires-Dist: z3-solver
Requires-Dist: rich
